{
  "type": "object",
  "description": "TagResourceRequest schema from Amazon AppFlow API",
  "properties": {
    "tags": {
      "type": "object",
      "description": "The tags used to organize, track, or control access for your flow.",
      "additionalProperties": {
        "type": "string"
      },
      "example": {
        "environment": "production",
        "team": "data-engineering"
      }
    }
  },
  "required": [
    "tags"
  ],
  "$schema": "https://json-structure.org/meta/core/v0/#",
  "$id": "https://raw.githubusercontent.com/api-evangelist/amazon-appflow/refs/heads/main/json-structure/appflow-tag-resource-request-structure.json"
}